[
    {
        "model": "users.user",
        "pk": 1,
        "fields":{
            "username": "Raphael1",
            "password": "pbkdf2_sha256$720000$zEawpgIRFYEkBUsFULokoN$mplBNzl2pN2H+pA3vrDkCrJOVRsl5uj/6hgVt1Rtrcs=",
            "email": "raphael1@gmail.com"
        }
    },
    {
        "model": "catalog.game",
        "pk": 1,
        "fields":{
            "title": "elden ring",
            "path": "img/2024/06/19/eld.jpg",
            "description": "adas", 
            "price": 255,
            "stocked": 12   
        }
    },
    {
        "model": "catalog.like",
        "pk": 1,
        "fields":{
            "game_id": 1,
            "user_id": 1  
        }
    },
    {
        "model": "catalog.comment",
        "pk": 1,
        "fields":{
            "content": "nvn",
            "user_id": 1,
            "game_id": 2
        }
    }
]